odoo9_addon_product_uom-9.0.1.0.1-py2.7-nspkg.pth
odoo_addons/product_uom/__openerp__.py
odoo_addons/product_uom/__init__.py
odoo_addons/product_uom/README.rst
odoo_addons/product_uom/data/product_uom_categ.xml
odoo_addons/product_uom/data/product_uom.xml
odoo_addons/product_uom/static/description/icon.png
odoo9_addon_product_uom-9.0.1.0.1.dist-info/top_level.txt
odoo9_addon_product_uom-9.0.1.0.1.dist-info/WHEEL
odoo9_addon_product_uom-9.0.1.0.1.dist-info/RECORD
odoo9_addon_product_uom-9.0.1.0.1.dist-info/metadata.json
odoo9_addon_product_uom-9.0.1.0.1.dist-info/DESCRIPTION.rst
odoo9_addon_product_uom-9.0.1.0.1.dist-info/METADATA
odoo9_addon_product_uom-9.0.1.0.1.dist-info/namespace_packages.txt
